{
  "node": {
    "003d8f912c9f4ed6675958d9a403f77216daf17ddb": {
      "workers": {
        "app/(commonLayout)/menu/[id]/page": {
          "moduleId": 47507,
          "async": false,
          "exportedName": "getMyNotificationsAction",
          "filename": "src/actions/notification.action.ts"
        }
      },
      "layer": {
        "app/(commonLayout)/menu/[id]/page": "action-browser"
      },
      "exportedName": "getMyNotificationsAction",
      "filename": "src/actions/notification.action.ts"
    },
    "4079d8303501e28eeaaca457cf6f2726318ddec8b7": {
      "workers": {
        "app/(commonLayout)/menu/[id]/page": {
          "moduleId": 47507,
          "async": false,
          "exportedName": "markNotificationReadAction",
          "filename": "src/actions/notification.action.ts"
        }
      },
      "layer": {
        "app/(commonLayout)/menu/[id]/page": "action-browser"
      },
      "exportedName": "markNotificationReadAction",
      "filename": "src/actions/notification.action.ts"
    },
    "402a24ccec08c02b4070c45bb41c7ea5cb886548ee": {
      "workers": {
        "app/(commonLayout)/menu/[id]/page": {
          "moduleId": 47507,
          "async": false,
          "exportedName": "getMenuItemById",
          "filename": "src/actions/menuItem.action.ts"
        }
      },
      "layer": {
        "app/(commonLayout)/menu/[id]/page": "action-browser"
      },
      "exportedName": "getMenuItemById",
      "filename": "src/actions/menuItem.action.ts"
    },
    "6082acd8510b9659976520e84dd1d62355230af8f6": {
      "workers": {
        "app/(commonLayout)/menu/[id]/page": {
          "moduleId": 47507,
          "async": false,
          "exportedName": "getReviewsAction",
          "filename": "src/actions/review.action.ts"
        }
      },
      "layer": {
        "app/(commonLayout)/menu/[id]/page": "action-browser"
      },
      "exportedName": "getReviewsAction",
      "filename": "src/actions/review.action.ts"
    },
    "60c75e5cacb2bd675064234916e5cd9416d539151f": {
      "workers": {
        "app/(commonLayout)/menu/[id]/page": {
          "moduleId": 47507,
          "async": false,
          "exportedName": "createReviewAction",
          "filename": "src/actions/review.action.ts"
        }
      },
      "layer": {
        "app/(commonLayout)/menu/[id]/page": "action-browser"
      },
      "exportedName": "createReviewAction",
      "filename": "src/actions/review.action.ts"
    },
    "40fe26b130c4e398627ce22be070371b5186f6c2de": {
      "workers": {
        "app/(commonLayout)/menu/[id]/page": {
          "moduleId": 47507,
          "async": false,
          "exportedName": "deleteReviewAction",
          "filename": "src/actions/review.action.ts"
        }
      },
      "layer": {
        "app/(commonLayout)/menu/[id]/page": "action-browser"
      },
      "exportedName": "deleteReviewAction",
      "filename": "src/actions/review.action.ts"
    }
  },
  "edge": {}
}